opendbt/__init__.py
opendbt/__main__.py
opendbt/examples.py
opendbt/logger.py
opendbt/runtime_patcher.py
opendbt/utils.py
opendbt/airflow/__init__.py
opendbt/airflow/plugin.py
opendbt/catalog/__init__.py
opendbt/dbt/__init__.py
opendbt/dbt/docs/.gitignore
opendbt/dbt/docs/index.html
opendbt/dbt/shared/__init__.py
opendbt/dbt/shared/adapters/__init__.py
opendbt/dbt/shared/adapters/impl.py
opendbt/dbt/shared/cli/__init__.py
opendbt/dbt/shared/cli/main.py
opendbt/dbt/shared/task/__init__.py
opendbt/dbt/shared/task/sqlfluff.py
opendbt/dbt/v17/__init__.py
opendbt/dbt/v17/adapters/__init__.py
opendbt/dbt/v17/adapters/factory.py
opendbt/dbt/v17/config/__init__.py
opendbt/dbt/v17/config/runtime.py
opendbt/dbt/v17/task/__init__.py
opendbt/dbt/v17/task/run.py
opendbt/dbt/v17/task/docs/__init__.py
opendbt/dbt/v17/task/docs/generate.py
opendbt/dbt/v18/__init__.py
opendbt/dbt/v18/adapters/__init__.py
opendbt/dbt/v18/adapters/factory.py
opendbt/dbt/v18/artifacts/__init__.py
opendbt/dbt/v18/artifacts/schemas/__init__.py
opendbt/dbt/v18/artifacts/schemas/run.py
opendbt/dbt/v18/config/__init__.py
opendbt/dbt/v18/config/runtime.py
opendbt/dbt/v18/task/__init__.py
opendbt/dbt/v18/task/run.py
opendbt/dbt/v18/task/docs/__init__.py
opendbt/dbt/v18/task/docs/generate.py
opendbt/macros/executedlt.sql
opendbt/macros/executepython.sql
opendbt/macros/executesql.sql
opendbt-0.14.0.dist-info/LICENSE
opendbt-0.14.0.dist-info/METADATA
opendbt-0.14.0.dist-info/WHEEL
opendbt-0.14.0.dist-info/entry_points.txt
opendbt-0.14.0.dist-info/top_level.txt
opendbt-0.14.0.dist-info/RECORD
