Metadata-Version: 2.1
Name: opendbt
Version: 0.14.0
Summary: opendbt dbt-core with additional features
Author: Memiiso Organization
License: Apache License 2.0
Project-URL: Homepage, https://github.com/memiiso/opendbt
Project-URL: Documentation, https://github.com/memiiso/opendbt
Project-URL: Repository, https://github.com/memiiso/opendbt
Keywords: dbt-core,dbt
Classifier: Development Status :: 5 - Production/Stable
Classifier: Programming Language :: Python :: 3
Requires-Python: >=3.8
License-File: LICENSE
Requires-Dist: dbt-duckdb >=1.6
Requires-Dist: sqlfluff
Requires-Dist: sqlfluff-templater-dbt
Requires-Dist: sqlglot
Requires-Dist: tqdm
Requires-Dist: filelock
Provides-Extra: airflow
Requires-Dist: apache-airflow ; extra == 'airflow'
Provides-Extra: dev
Requires-Dist: mkdocs-material ; extra == 'dev'
Provides-Extra: test
Requires-Dist: testcontainers >=4.10 ; extra == 'test'
Requires-Dist: apache-airflow ; extra == 'test'
Requires-Dist: pylint ; extra == 'test'
Requires-Dist: dlt[duckdb] ; extra == 'test'
